seaplane/apps/__init__.py
seaplane/apps/cli.py
seaplane/apps/resources/app-template/cookiecutter.json
seaplane/apps/resources/app-template/{{cookiecutter.project_slug}}/.env
seaplane/apps/resources/app-template/{{cookiecutter.project_slug}}/.gitignore
seaplane/apps/resources/app-template/{{cookiecutter.project_slug}}/README.md
seaplane/apps/resources/app-template/{{cookiecutter.project_slug}}/pyproject.toml
seaplane/apps/resources/app-template/{{cookiecutter.project_slug}}/{{cookiecutter.project_slug}}/main.py
seaplane/collector.py
seaplane/config.py
seaplane/deploy/__init__.py
seaplane/deploy/resources/Dockerfile
seaplane/deploy/resources/entrypoint.sh
seaplane/deploy/resources/setup.sh
seaplane/deploy/resources/webhook-replicate.sh
seaplane/deploy/utils.py
seaplane/errors.py
seaplane/kv.py
seaplane/logs.py
seaplane/modelhub.py
seaplane/object.py
seaplane/pipes/__init__.py
seaplane/pipes/debug_schema.py
seaplane/pipes/executor.py
seaplane/pipes/status.py
seaplane/run_load_dotenv.py
seaplane/sdk_internal_utils/__init__.py
seaplane/sdk_internal_utils/buckets.py
seaplane/sdk_internal_utils/http.py
seaplane/sdk_internal_utils/retry.py
seaplane/sdk_internal_utils/token_api.py
seaplane/sdk_internal_utils/token_auth.py
seaplane/sql.py
seaplane/substation.py
seaplane/vector.py
seaplane-0.6.16.dist-info/METADATA
seaplane-0.6.16.dist-info/WHEEL
seaplane-0.6.16.dist-info/entry_points.txt
seaplane-0.6.16.dist-info/RECORD
